salestax.py
salestax-1.0.0.dist-info/METADATA
salestax-1.0.0.dist-info/WHEEL
salestax-1.0.0.dist-info/licenses/LICENSE
salestax-1.0.0.dist-info/RECORD
