Metadata-Version: 2.1
Name: salestax
Version: 1.0.0
Summary: Get Sales Tax Rates. Currently only supports Arkansas (because that is the only one I need) but I am open to pull requests for other states.
Author-email: Justin Kumpe <jakumpe@kumpes.com>
License-Expression: MIT
License-File: LICENSE
Classifier: License :: OSI Approved :: MIT License
Classifier: Natural Language :: English
Classifier: Operating System :: OS Independent
Classifier: Programming Language :: Python :: 3
Requires-Python: >=3.9
Requires-Dist: beautifulsoup4
Requires-Dist: requests
